{
  "chunk_id": "documents_page_5_037442dd__638d706a4b2e__chunk_0000_part_1",
  "document_id": "documents_page_5_037442dd__638d706a4b2e",
  "parent_document": "documents_page_5_037442dd__638d706a4b2e",
  "chunk_index": 0,
  "total_chunks": 2,
  "previous_chunk_id": "",
  "next_chunk_id": "documents_page_5_037442dd__638d706a4b2e__chunk_0001",
  "title": "More Menu (Part 2/2)",
  "url": "https://westtripura.nic.in/documents/page/5/",
  "heading_chain": [
    "Documents"
  ],
  "heading": "Documents",
  "section": "Documents",
  "sub_section": "",
  "text": "| 18/06/2021 | |\n| Order under section 144 Cr.PC of corona day curfew from 2 P.M to 6 P.M of 18th june ,2021 and Corona night curfew from 6P.M to5 A.M of 19th june 2021. | 11/06/2021 | |\n| Order under section 144 Cr.PC of corona day curfew upto 4 P.M of 5th june , 2021 and Corona night curfew upto 5 A.M of 6th june 2021. | 05/06/2021 | |\n| Facilitating citizen to book vaccination slot through Common Service Centres (CSC) – reg. | 04/06/2021 | |\n| Corona Day/Night Curfew order Under Disaster Management Act’2005 & Epidemic Diseases Act’1897 | 29/05/2021 | |\n| NOTICE INVITING TENDER RELATED TO MGNREGS ACCOUNTS FOR WEST TRIPURA DISTRICT | 28/05/2021 | |",
  "content": "| 18/06/2021 | |\n| Order under section 144 Cr.PC of corona day curfew from 2 P.M to 6 P.M of 18th june ,2021 and Corona night curfew from 6P.M to5 A.M of 19th june 2021. | 11/06/2021 | |\n| Order under section 144 Cr.PC of corona day curfew upto 4 P.M of 5th june , 2021 and Corona night curfew upto 5 A.M of 6th june 2021. | 05/06/2021 | |\n| Facilitating citizen to book vaccination slot through Common Service Centres (CSC) – reg. | 04/06/2021 | |\n| Corona Day/Night Curfew order Under Disaster Management Act’2005 & Epidemic Diseases Act’1897 | 29/05/2021 | |\n| NOTICE INVITING TENDER RELATED TO MGNREGS ACCOUNTS FOR WEST TRIPURA DISTRICT | 28/05/2021 | |",
  "language": "en",
  "content_type": "semantic_chunk",
  "token_count": 161,
  "character_count": 657,
  "has_table": true,
  "has_list": true,
  "created_at": "2026-07-11T20:35:26.802598Z",
  "sha256": "78ff09ad95fd6d819b6c45b3dde53f6f18851bd7e75d359cae1b479fb5a8bd55",
  "split_part": 1,
  "split_total": 2
}