{
  "chunk_id": "bn_e0_a6_a8_e0_a6_bf_e0_a6_b0_e0_a7_8d_e0_a6_ac_e0_a6_be_e0_a6_9a_e0_a6_a8_8e69f068__25bc21dbf209__chunk_0000",
  "document_id": "bn_e0_a6_a8_e0_a6_bf_e0_a6_b0_e0_a7_8d_e0_a6_ac_e0_a6_be_e0_a6_9a_e0_a6_a8_8e69f068__25bc21dbf209",
  "parent_document": "bn_e0_a6_a8_e0_a6_bf_e0_a6_b0_e0_a7_8d_e0_a6_ac_e0_a6_be_e0_a6_9a_e0_a6_a8_8e69f068__25bc21dbf209",
  "chunk_index": 0,
  "total_chunks": 1,
  "previous_chunk_id": "",
  "next_chunk_id": "",
  "title": "More Menu",
  "url": "https://westtripura.nic.in/bn/%e0%a6%a8%e0%a6%bf%e0%a6%b0%e0%a7%8d%e0%a6%ac%e0%a6%be%e0%a6%9a%e0%a6%a8/",
  "heading_chain": [
    "নির্বাচন"
  ],
  "heading": "নির্বাচন",
  "section": "নির্বাচন",
  "sub_section": "",
  "text": "# নির্বাচন\n\nজেলা প্রশাসনের মালিকানাধীন সামগ্রী\n[ জাতীয় সূচনা বিজ্ঞান কেন্দ্র ] দ্বারা প্রস্তুত এবং হোস্ট করা,",
  "content": "# নির্বাচন\n\nজেলা প্রশাসনের মালিকানাধীন সামগ্রী\n[ জাতীয় সূচনা বিজ্ঞান কেন্দ্র ] দ্বারা প্রস্তুত এবং হোস্ট করা,",
  "language": "en",
  "content_type": "semantic_chunk",
  "token_count": 126,
  "character_count": 110,
  "has_table": false,
  "has_list": false,
  "created_at": "2026-07-11T20:31:11.549389Z",
  "sha256": "85e43fb09263d046357be9d6e54a80378361a00c108e6091646e60064fcd5de5"
}