{
  "chunk_id": "service_social_security_a18fc85c__a1ec480472e0__chunk_0000",
  "document_id": "service_social_security_a18fc85c__a1ec480472e0",
  "parent_document": "service_social_security_a18fc85c__a1ec480472e0",
  "chunk_index": 0,
  "total_chunks": 1,
  "previous_chunk_id": "",
  "next_chunk_id": "",
  "title": "More Menu",
  "url": "https://westtripura.nic.in/service/social-security/",
  "heading_chain": [
    "Social Security",
    "SDM Office Sadar"
  ],
  "heading": "Social Security",
  "section": "Social Security",
  "sub_section": "SDM Office Sadar",
  "text": "# Social Security\n\nCitizen can avail different types of Social Services using below web link.\n**Visit** :\n\n## SDM Office Sadar\n\nOffice of the SDM, Sadar Sub Division, Office Lane, Agartala\n**Location** : Office Lane | **City** : Agartala | **PIN Code** : 799001\n**Email** : dmwest-tr[at]nic[dot]in",
  "content": "# Social Security\n\nCitizen can avail different types of Social Services using below web link.\n**Visit** :\n\n## SDM Office Sadar\n\nOffice of the SDM, Sadar Sub Division, Office Lane, Agartala\n**Location** : Office Lane | **City** : Agartala | **PIN Code** : 799001\n**Email** : dmwest-tr[at]nic[dot]in",
  "language": "en",
  "content_type": "semantic_chunk",
  "token_count": 85,
  "character_count": 297,
  "has_table": false,
  "has_list": false,
  "created_at": "2026-07-11T20:34:23.131178Z",
  "sha256": "e62cdc47fd25177af44b45cc23f10751231beb49af04cd6ffdda82e6cee9dca4"
}