{
  "chunk_id": "past_notices_tenders_page_5_0b34c798__41b0064e1918__chunk_0001",
  "document_id": "past_notices_tenders_page_5_0b34c798__41b0064e1918",
  "parent_document": "past_notices_tenders_page_5_0b34c798__41b0064e1918",
  "chunk_index": 1,
  "total_chunks": 2,
  "previous_chunk_id": "past_notices_tenders_page_5_0b34c798__41b0064e1918__chunk_0000",
  "next_chunk_id": "",
  "title": "More Menu",
  "url": "https://westtripura.nic.in/past-notices/tenders/page/5",
  "heading_chain": [
    "Tenders"
  ],
  "heading": "Tenders",
  "section": "Tenders",
  "sub_section": "",
  "text": "| Title | Description | Start Date | End Date | File |\n| Notice of Inviting a Tender for the Hiring of Maruti Eeco Vehicles, including Fuel and Driver, for Use in the Office of the Collector of Excise, West Tripura District. | | 18/01/2024 | 25/01/2024 | |\n| E-Tender for hiring Maruti ECO Vehicle (CNG), including fuel and driver of the hired vehicle, for District Mission Manager Unit, West Tripura, Agartala. | | 23/11/2023 | 05/12/2023 | |\n\n* **[« Prev]**\n* **[1]**\n* **[2]**\n* **[3]**\n* **[4]**\n* **[6]**\n* **[7]**\n* **[8]**\n* **[9]**\n* ...\n* **[28]**\n* **[Next » ]**",
  "content": "| Title | Description | Start Date | End Date | File |\n| Notice of Inviting a Tender for the Hiring of Maruti Eeco Vehicles, including Fuel and Driver, for Use in the Office of the Collector of Excise, West Tripura District. | | 18/01/2024 | 25/01/2024 | |\n| E-Tender for hiring Maruti ECO Vehicle (CNG), including fuel and driver of the hired vehicle, for District Mission Manager Unit, West Tripura, Agartala. | | 23/11/2023 | 05/12/2023 | |\n\n* **[« Prev]**\n* **[1]**\n* **[2]**\n* **[3]**\n* **[4]**\n* **[6]**\n* **[7]**\n* **[8]**\n* **[9]**\n* ...\n* **[28]**\n* **[Next » ]**",
  "language": "en",
  "content_type": "semantic_chunk",
  "token_count": 198,
  "character_count": 572,
  "has_table": true,
  "has_list": true,
  "created_at": "2026-07-11T20:35:54.336384Z",
  "sha256": "2ea608d84cf8d00cccc34b9fb3dcf6b10de13e105c19e24523dcb6021ff60f14"
}