{
  "chunk_id": "sch_html_6cf6c508__2f26f8841922__chunk_0001",
  "document_id": "sch_html_6cf6c508__2f26f8841922",
  "parent_document": "sch_html_6cf6c508__2f26f8841922",
  "chunk_index": 1,
  "total_chunks": 2,
  "previous_chunk_id": "sch_html_6cf6c508__2f26f8841922__chunk_0000",
  "next_chunk_id": "",
  "title": "sch.html  6cf6c508",
  "url": "https://www.wptripura.nic.in/sch.html",
  "heading_chain": [
    "sch.html  6cf6c508"
  ],
  "heading": "sch.html  6cf6c508",
  "section": "sch.html  6cf6c508",
  "sub_section": "",
  "text": "| Designation | Lecturer | |\n| Qualification | B.E in Civil Engineering,M.Tech in Geotechnical Engineering |\n| Areas of Interest | Soil investigation and Exploration, Soil stabilization, Mechanics of soil. |\n| Email: | suvranit@gmail.com |\n| Contact: | 7005368021 |\n| Web Profile | |\n\n| **7. Smt Priyanka Banik****(Civil)\n** |\n\n| Designation | Lecturer (Contractual) | |\n| Qualification | B.E. in Civil Engineering |\n| Areas of Interest | Mechanics, Environmental Engineering, Building Materials |\n| Email: | priyankabanik.jp@gmail.com |\n| Contact: | 9774122410 |\n| Web Profile | |",
  "content": "| Designation | Lecturer | |\n| Qualification | B.E in Civil Engineering,M.Tech in Geotechnical Engineering |\n| Areas of Interest | Soil investigation and Exploration, Soil stabilization, Mechanics of soil. |\n| Email: | suvranit@gmail.com |\n| Contact: | 7005368021 |\n| Web Profile | |\n\n| **7. Smt Priyanka Banik****(Civil)\n** |\n\n| Designation | Lecturer (Contractual) | |\n| Qualification | B.E. in Civil Engineering |\n| Areas of Interest | Mechanics, Environmental Engineering, Building Materials |\n| Email: | priyankabanik.jp@gmail.com |\n| Contact: | 9774122410 |\n| Web Profile | |",
  "language": "en",
  "content_type": "semantic_chunk",
  "token_count": 151,
  "character_count": 581,
  "has_table": true,
  "has_list": false,
  "created_at": "2026-07-11T20:41:43.793877Z",
  "sha256": "af3262e29e68ef9bf305d3297c120daacd0b097091d10b6de1d48bf90e4dfbf0"
}