{
  "document_id": "Admission_20lateral_20entry_html_bf504d7c_d928be30a8b4_md",
  "source_path": "Admission_20lateral_20entry_html_bf504d7c__d928be30a8b4.md",
  "title": "Admission 20lateral 20entry.html  bf504d7c",
  "metadata": {
    "document_id": "Admission_20lateral_20entry_html_bf504d7c__d928be30a8b4",
    "source_path": "Admission_20lateral_20entry.html__bf504d7c.md",
    "url": "https://www.wptripura.nic.in/Admission%20lateral%20entry.html",
    "depth": "4",
    "crawled_at": "2026-07-11T20:38:05.130021Z",
    "title": "Admission 20lateral 20entry.html  bf504d7c",
    "content": "---\nurl: https://www.wptripura.nic.in/Admission%20lateral%20entry.html\ndepth: 4\nscore: 0\ncrawled_at: 2026-07-11T20:38:05.130021Z\n---\n| |\n| --- |\n\n| --- |\n\n**[Scholarships](https://www.wptripura.nic.in/scholarships.html)**\n\n**[ NEWSLETTERS](https://www.wptripura.nic.in/Newsletter.html)\n\n**\n\n**\n\n[Admission through ITI Lateral Entry Scheme](https://www.wptripura.nic.in/Admission%20lateral%20entry.html) [](https://www.wptripura.nic.in/images/EVEN%20Sementer%20On%20line%20Class%202021.pdf)**\n\n| **\nAdmission through ITI Lateral Entry Scheme - 2021\n\n** |\n| --- |\n\n* [ Publication of provisional rejection list of ITI candidates applied for Diploma Engineering Admission through Lateral Entry 2021 ](https://www.wptripura.nic.in/images/ITI%20Lateral%20Entry_Provisional%20Rejection%20List.pdf)**[](https://www.wptripura.nic.in/images/EVEN%20Sementer%20On%20line%20Class%202021.pdf)**\n* [ Notice for NOC for in service ITI pass candidates](https://www.wptripura.nic.in/images/Notice%20for%20NOC%20for%20Inservice%20ITI%20pass%20candidates.pdf)**[](https://www.wptripura.nic.in/images/EVEN%20Sementer%20On%20line%20Class%202021.pdf)**\n* [Advertisement of Central Selection Committee- 2021, Education (Higher) Department](https://www.wptripura.nic.in/images/CSC.jpeg)**[](https://www.wptripura.nic.in/images/EVEN%20Sementer%20On%20line%20Class%202021.pdf)**\n* [Detail Notification of Lateral Entry Admission into 3rd semester of Diploma Engineering from ITI ](https://www.wptripura.nic.in/images/Detail%20Notification.pdf) **[](https://www.wptripura.nic.in/images/EVEN%20Sementer%20On%20line%20Class%202021.pdf)**\n* [Prospectus cum Information Bulletin of Lateral Entry Admission into 3rd semester of Diploma Engineering from ITI ](https://www.wptripura.nic.in/images/ITI_Lateral_Prospectus_2021.pdf) **[](https://www.wptripura.nic.in/images/EVEN%20Sementer%20On%20line%20Class%202021.pdf)**\n\n| |\n| --- |",
    "language": "en",
    "content_hash": "9e56cbb346e2e4106779b3040696f3b1d8d38abb672970fdb18330bc6c4d17f4",
    "metadata": {
      "source_path": "Admission_20lateral_20entry.html__bf504d7c.md",
      "url": "https://www.wptripura.nic.in/Admission%20lateral%20entry.html",
      "depth": 4,
      "crawled_at": "2026-07-11T20:38:05.130021Z",
      "language": "en",
      "content_hash": "9e56cbb346e2e4106779b3040696f3b1d8d38abb672970fdb18330bc6c4d17f4"
    },
    "score": "0"
  },
  "tree": {
    "type": "document",
    "title": "Document",
    "level": 0,
    "text": "",
    "metadata": {
      "source_path": "Admission_20lateral_20entry_html_bf504d7c__d928be30a8b4.md"
    },
    "children": [
      {
        "type": "paragraph",
        "title": "",
        "level": 0,
        "text": "| |\n| --- |",
        "metadata": {
          "links": [],
          "images": []
        },
        "children": []
      },
      {
        "type": "paragraph",
        "title": "",
        "level": 0,
        "text": "| --- |",
        "metadata": {
          "links": [],
          "images": []
        },
        "children": []
      },
      {
        "type": "paragraph",
        "title": "",
        "level": 0,
        "text": "**[Scholarships](https://www.wptripura.nic.in/scholarships.html)**",
        "metadata": {
          "links": [
            {
              "href": "https://www.wptripura.nic.in/scholarships.html",
              "text": ""
            }
          ],
          "images": []
        },
        "children": []
      },
      {
        "type": "paragraph",
        "title": "",
        "level": 0,
        "text": "**[ NEWSLETTERS](https://www.wptripura.nic.in/Newsletter.html)",
        "metadata": {
          "links": [
            {
              "href": "https://www.wptripura.nic.in/Newsletter.html",
              "text": ""
            }
          ],
          "images": []
        },
        "children": []
      },
      {
        "type": "paragraph",
        "title": "",
        "level": 0,
        "text": "**",
        "metadata": {
          "links": [],
          "images": []
        },
        "children": []
      },
      {
        "type": "paragraph",
        "title": "",
        "level": 0,
        "text": "**",
        "metadata": {
          "links": [],
          "images": []
        },
        "children": []
      },
      {
        "type": "paragraph",
        "title": "",
        "level": 0,
        "text": "[Admission through ITI Lateral Entry Scheme](https://www.wptripura.nic.in/Admission%20lateral%20entry.html) [](https://www.wptripura.nic.in/images/EVEN%20Sementer%20On%20line%20Class%202021.pdf)**",
        "metadata": {
          "links": [
            {
              "href": "https://www.wptripura.nic.in/Admission%20lateral%20entry.html",
              "text": ""
            },
            {
              "href": "https://www.wptripura.nic.in/images/EVEN%20Sementer%20On%20line%20Class%202021.pdf",
              "text": ""
            }
          ],
          "images": []
        },
        "children": []
      },
      {
        "type": "paragraph",
        "title": "",
        "level": 0,
        "text": "| **\nAdmission through ITI Lateral Entry Scheme - 2021",
        "metadata": {
          "links": [],
          "images": []
        },
        "children": []
      },
      {
        "type": "paragraph",
        "title": "",
        "level": 0,
        "text": "** |\n| --- |",
        "metadata": {
          "links": [],
          "images": []
        },
        "children": []
      },
      {
        "type": "list",
        "title": "",
        "level": 0,
        "text": "",
        "metadata": {
          "ordered": false,
          "items": [
            "[ Publication of provisional rejection list of ITI candidates applied for Diploma Engineering Admission through Lateral Entry 2021 ](https://www.wptripura.nic.in/images/ITI%20Lateral%20Entry_Provisional%20Rejection%20List.pdf)**[](https://www.wptripura.nic.in/images/EVEN%20Sementer%20On%20line%20Class%202021.pdf)**",
            "[ Notice for NOC for in service ITI pass candidates](https://www.wptripura.nic.in/images/Notice%20for%20NOC%20for%20Inservice%20ITI%20pass%20candidates.pdf)**[](https://www.wptripura.nic.in/images/EVEN%20Sementer%20On%20line%20Class%202021.pdf)**",
            "[Advertisement of Central Selection Committee- 2021, Education (Higher) Department](https://www.wptripura.nic.in/images/CSC.jpeg)**[](https://www.wptripura.nic.in/images/EVEN%20Sementer%20On%20line%20Class%202021.pdf)**",
            "[Detail Notification of Lateral Entry Admission into 3rd semester of Diploma Engineering from ITI ](https://www.wptripura.nic.in/images/Detail%20Notification.pdf) **[](https://www.wptripura.nic.in/images/EVEN%20Sementer%20On%20line%20Class%202021.pdf)**",
            "[Prospectus cum Information Bulletin of Lateral Entry Admission into 3rd semester of Diploma Engineering from ITI ](https://www.wptripura.nic.in/images/ITI_Lateral_Prospectus_2021.pdf) **[](https://www.wptripura.nic.in/images/EVEN%20Sementer%20On%20line%20Class%202021.pdf)**"
          ]
        },
        "children": []
      },
      {
        "type": "paragraph",
        "title": "",
        "level": 0,
        "text": "[ Publication of provisional rejection list of ITI candidates applied for Diploma Engineering Admission through Lateral Entry 2021 ](https://www.wptripura.nic.in/images/ITI%20Lateral%20Entry_Provisional%20Rejection%20List.pdf)**[](https://www.wptripura.nic.in/images/EVEN%20Sementer%20On%20line%20Class%202021.pdf)**",
        "metadata": {
          "links": [
            {
              "href": "https://www.wptripura.nic.in/images/ITI%20Lateral%20Entry_Provisional%20Rejection%20List.pdf",
              "text": ""
            },
            {
              "href": "https://www.wptripura.nic.in/images/EVEN%20Sementer%20On%20line%20Class%202021.pdf",
              "text": ""
            }
          ],
          "images": []
        },
        "children": []
      },
      {
        "type": "paragraph",
        "title": "",
        "level": 0,
        "text": "[ Notice for NOC for in service ITI pass candidates](https://www.wptripura.nic.in/images/Notice%20for%20NOC%20for%20Inservice%20ITI%20pass%20candidates.pdf)**[](https://www.wptripura.nic.in/images/EVEN%20Sementer%20On%20line%20Class%202021.pdf)**",
        "metadata": {
          "links": [
            {
              "href": "https://www.wptripura.nic.in/images/Notice%20for%20NOC%20for%20Inservice%20ITI%20pass%20candidates.pdf",
              "text": ""
            },
            {
              "href": "https://www.wptripura.nic.in/images/EVEN%20Sementer%20On%20line%20Class%202021.pdf",
              "text": ""
            }
          ],
          "images": []
        },
        "children": []
      },
      {
        "type": "paragraph",
        "title": "",
        "level": 0,
        "text": "[Advertisement of Central Selection Committee- 2021, Education (Higher) Department](https://www.wptripura.nic.in/images/CSC.jpeg)**[](https://www.wptripura.nic.in/images/EVEN%20Sementer%20On%20line%20Class%202021.pdf)**",
        "metadata": {
          "links": [
            {
              "href": "https://www.wptripura.nic.in/images/CSC.jpeg",
              "text": ""
            },
            {
              "href": "https://www.wptripura.nic.in/images/EVEN%20Sementer%20On%20line%20Class%202021.pdf",
              "text": ""
            }
          ],
          "images": []
        },
        "children": []
      },
      {
        "type": "paragraph",
        "title": "",
        "level": 0,
        "text": "[Detail Notification of Lateral Entry Admission into 3rd semester of Diploma Engineering from ITI ](https://www.wptripura.nic.in/images/Detail%20Notification.pdf) **[](https://www.wptripura.nic.in/images/EVEN%20Sementer%20On%20line%20Class%202021.pdf)**",
        "metadata": {
          "links": [
            {
              "href": "https://www.wptripura.nic.in/images/Detail%20Notification.pdf",
              "text": ""
            },
            {
              "href": "https://www.wptripura.nic.in/images/EVEN%20Sementer%20On%20line%20Class%202021.pdf",
              "text": ""
            }
          ],
          "images": []
        },
        "children": []
      },
      {
        "type": "paragraph",
        "title": "",
        "level": 0,
        "text": "[Prospectus cum Information Bulletin of Lateral Entry Admission into 3rd semester of Diploma Engineering from ITI ](https://www.wptripura.nic.in/images/ITI_Lateral_Prospectus_2021.pdf) **[](https://www.wptripura.nic.in/images/EVEN%20Sementer%20On%20line%20Class%202021.pdf)**",
        "metadata": {
          "links": [
            {
              "href": "https://www.wptripura.nic.in/images/ITI_Lateral_Prospectus_2021.pdf",
              "text": ""
            },
            {
              "href": "https://www.wptripura.nic.in/images/EVEN%20Sementer%20On%20line%20Class%202021.pdf",
              "text": ""
            }
          ],
          "images": []
        },
        "children": []
      },
      {
        "type": "paragraph",
        "title": "",
        "level": 0,
        "text": "| |\n| --- |",
        "metadata": {
          "links": [],
          "images": []
        },
        "children": []
      }
    ]
  }
}